Data_Generators/Data_Gen_Performance.py
Data_Generators/Data_Generation_performance.py
Data_Generators/Dense_Data_Generator.py
Data_Generators/General_Data_Features.py
Data_Generators/Sparse_Data_Generator.py
Data_Generators/Tokenizing_Text_Data.py
Data_Generators/__init__.py
Data_Generators/data_generator.py
EDA/EDA.py
EDA/__init__.py
EDA/dimensionality.py
ETL/CSV_ETL.py
ETL/DataBase_ETL.py
ETL/ETL_pipeline.py
ETL/__init__.py
Loaders/Custom_loader.py
Loaders/Loaders_Performance.py
Loaders/Vector_database.py
Loaders/__init__.py
Loaders/csv_loader.py
Loaders/s3_loader.py
Loaders/sql_loader.py
Loaders/test_csv_loader.py
VoltForm/Main.py
VoltForm/Monitoring.py
VoltForm/Validator.py
VoltForm/Visualize_and_provision.py
VoltForm/__init__.py
VoltForm/base.py
VoltForm/compute_cluster.py
VoltForm/engine.py
VoltForm/etl_pipeline.py
VoltForm/parser.py
VoltForm/storage.py
preprocess/Cleaning.py
preprocess/__init__.py
preprocess/encoding.py
preprocess/pipeline.py
preprocess/scaling.py
DataVolt-0.0.1.dist-info/LICENSE.md
DataVolt-0.0.1.dist-info/METADATA
DataVolt-0.0.1.dist-info/WHEEL
DataVolt-0.0.1.dist-info/top_level.txt
DataVolt-0.0.1.dist-info/RECORD
