Metadata-Version: 2.2
Name: DataVolt
Version: 0.0.1
Summary: A reusable workflow for data engineering pipelines
Home-page: https://github.com/DarkStarStrix/DataVolt
Author: Allan
Author-email: allanw.mk@gmail.com
Classifier: Programming Language :: Python :: 3
Classifier: License :: OSI Approved :: MIT License
Classifier: Operating System :: OS Independent
Requires-Python: >=3.10
License-File: LICENSE.md
Dynamic: author
Dynamic: author-email
Dynamic: classifier
Dynamic: description
Dynamic: description-content-type
Dynamic: home-page
Dynamic: requires-python
Dynamic: summary
